{"cameraMode":{"drawMode":0,"name":"Shaded","section":"Shading Mode"},"sceneLighting":true,"audioPlay":false,"sceneViewState":{"showFog":true,"showMaterialUpdate":false,"showSkybox":true,"showFlares":true,"showImageEffects":true,"showParticleSystems":true},"in2DMode":false,"pivot":{"x":192.531005859375,"y":132.82432556152345,"z":-120.1264419555664},"rotation":{"x":0.30624011158943179,"y":-0.27561479806900027,"z":0.0931195542216301,"w":0.9064117670059204},"size":7.613280296325684,"orthographic":false}